my_clock/__init__.py
my_clock/my_clock.py
my_clock-0.2.5.dist-info/DESCRIPTION.rst
my_clock-0.2.5.dist-info/METADATA
my_clock-0.2.5.dist-info/RECORD
my_clock-0.2.5.dist-info/WHEEL
my_clock-0.2.5.dist-info/entry_points.txt
my_clock-0.2.5.dist-info/metadata.json
my_clock-0.2.5.dist-info/top_level.txt
