Metadata-Version: 2.0
Name: my-clock
Version: 0.2.5
Summary: my clock
Home-page: https://github.com/yassu/MyClock
Author: Yassu
Author-email: mathyassu@gmail.com
License: MIT
Platform: UNKNOWN
Classifier: Development Status :: 4 - Beta
Classifier: Environment :: Console
Classifier: License :: OSI Approved :: MIT License
Classifier: Programming Language :: Python
Classifier: Programming Language :: Python :: 3
Classifier: Programming Language :: Python :: 3.3
Classifier: Programming Language :: Python :: 3.4
Classifier: Topic :: Utilities
Requires-Dist: json5
Requires-Dist: pyaudio
Requires-Dist: tqdm
